scboolseq/__init__.py
scboolseq/_core_utils.py
scboolseq/_exceptions.py
scboolseq/_scboolseq_core.py
scboolseq/_types.py
scboolseq/binarization.py
scboolseq/simulation.py
scboolseq/utils.py
scboolseq/experimental/__init__.py
scboolseq/experimental/size_factors.py
scboolseq/meta/__init__.py
scboolseq/meta/aggregations.py
scboolseq/meta/bootstrap.py
scboolseq/meta/metrics.py
scboolseq-2.3.2.dist-info/METADATA
scboolseq-2.3.2.dist-info/WHEEL
scboolseq-2.3.2.dist-info/top_level.txt
scboolseq-2.3.2.dist-info/RECORD
