Metadata-Version: 2.4
Name: scBoolSeq
Version: 2.3.2
Summary: scBoolSeq: Linking scRNA-Seq Statistics and Boolean Dynamics.
Home-page: https://github.com/bnediction/scBoolSeq
Author: Gustavo Magaña López
Author-email: gustavo.magana@labri.fr
License: BSD-3
Classifier: Intended Audience :: Science/Research
Classifier: Topic :: Scientific/Engineering
Classifier: Topic :: Scientific/Engineering :: Bio-Informatics
Requires-Dist: pandas
Requires-Dist: diptest
Requires-Dist: scikit-learn>=1.6.0
Requires-Dist: statsmodels
Dynamic: author
Dynamic: author-email
Dynamic: classifier
Dynamic: description
Dynamic: description-content-type
Dynamic: home-page
Dynamic: keywords
Dynamic: license
Dynamic: requires-dist
Dynamic: summary
